tollingvision_scsinfo/TollingVisionService_pb2.py
tollingvision_scsinfo/TollingVisionService_pb2_grpc.py
tollingvision_scsinfo/__init__.py
tollingvision_scsinfo-2.6.2.dist-info/METADATA
tollingvision_scsinfo-2.6.2.dist-info/WHEEL
tollingvision_scsinfo-2.6.2.dist-info/licenses/LICENSE
tollingvision_scsinfo-2.6.2.dist-info/RECORD
