Metadata-Version: 2.4
Name: tollingvision_scsinfo
Version: 2.6.2
Summary: Python client for Tolling Vision
Project-URL: Homepage, https://tollingvision.com
Author-email: Tolling Vision <info@tollingvision.com>
License-File: LICENSE
Classifier: License :: OSI Approved :: MIT License
Classifier: Operating System :: OS Independent
Classifier: Programming Language :: Python :: 3
Requires-Python: >=3.6
